bipl/__init__.py
bipl/_env.py
bipl/_fileio.py
bipl/_types.py
bipl/cov.py
bipl/py.typed
bipl/io/__init__.py
bipl/io/_dzi.py
bipl/io/_gdal.py
bipl/io/_libs.py
bipl/io/_openslide.py
bipl/io/_slide.py
bipl/io/_slide_bases.py
bipl/io/_tiff.py
bipl/io/_tiff_compressions.py
bipl/io/_util.py
bipl/io/libs/libopenslide-1.dll
bipl/ops/__init__.py
bipl/ops/_mosaic.py
bipl/ops/_norm.py
bipl/ops/_tile.py
bipl/ops/_util.py
bipl-0.6.6.dist-info/METADATA
bipl-0.6.6.dist-info/WHEEL
bipl-0.6.6.dist-info/licenses/LICENSE
bipl-0.6.6.dist-info/RECORD
